reckomate_sdk/__init__.py
reckomate_sdk/client.py
reckomate_sdk/exceptions.py
reckomate_sdk/services/__init__.py
reckomate_sdk/services/admin.py
reckomate_sdk/services/excel_service.py
reckomate_sdk/services/interview_logic_service.py
reckomate_sdk/services/interview_realtime_service.py
reckomate_sdk/services/interview_scheduler_service.py
reckomate_sdk/services/leaderboard_service.py
reckomate_sdk/services/linktestwithphone_service.py
reckomate_sdk/services/mcq_schedule_service.py
reckomate_sdk/services/mcq_service.py
reckomate_sdk/services/qdrant_service.py
reckomate_sdk/services/question.py
reckomate_sdk/services/user_mcq_service.py
reckomate_sdk/services/users.py
reckomate_sdk/services/users_ingest.py
reckomate_sdk/services/usertest_service.py
recko_ai_sdk-1.1.0.dist-info/METADATA
recko_ai_sdk-1.1.0.dist-info/WHEEL
recko_ai_sdk-1.1.0.dist-info/top_level.txt
recko_ai_sdk-1.1.0.dist-info/RECORD
