Metadata-Version: 2.4
Name: recko-ai-sdk
Version: 1.1.0
Summary: Reckomate Python SDK
Requires-Python: >=3.10
Requires-Dist: requests>=2.31.0
